{
	"title": "Harry Potter and the Methods of Rationality",
	"creator": "Eliezer Yudkowsky",
	"filters": [
		"from-url",
		"hpmor",
        "typography",
		"finalize"
	],
	"filename": "Harry Potter and the Methods of Rationality",
	"output": ["epub", "latex", "html"],
	"contents":
    [
        {
            "title": "A Day of Very Low Probability",
            "src": "http://www.hpmor.com/chapter/1"
        },
        {
            "title": "Everything I Believe Is False",
            "src": "http://www.hpmor.com/chapter/2"
        },
        {
            "title": "Comparing Reality To Its Alternatives",
            "src": "http://www.hpmor.com/chapter/3"
        },
        {
            "title": "The Efficient Market Hypothesis",
            "src": "http://www.hpmor.com/chapter/4"
        },
        {
            "title": "The Fundamental Attribution Error",
            "src": "http://www.hpmor.com/chapter/5"
        },
        {
            "title": "The Planning Fallacy",
            "src": "http://www.hpmor.com/chapter/6"
        },
        {
            "title": "Reciprocation",
            "src": "http://www.hpmor.com/chapter/7"
        },
        {
            "title": "Positive Bias",
            "src": "http://www.hpmor.com/chapter/8"
        },
        {
            "title": "Title Redacted, Part I",
            "src": "http://www.hpmor.com/chapter/9"
        },
        {
            "title": "Self Awareness, Part II",
            "src": "http://www.hpmor.com/chapter/10"
        },
        {
            "title": "Omake Files 1, 2, 3",
            "src": "http://www.hpmor.com/chapter/11"
        },
        {
            "title": "Impulse Control",
            "src": "http://www.hpmor.com/chapter/12"
        },
        {
            "title": "Asking the Wrong Questions",
            "src": "http://www.hpmor.com/chapter/13"
        },
        {
            "title": "The Unknown and the Unknowable",
            "src": "http://www.hpmor.com/chapter/14"
        },
        {
            "title": "Conscientiousness",
            "src": "http://www.hpmor.com/chapter/15"
        },
        {
            "title": "Lateral Thinking",
            "src": "http://www.hpmor.com/chapter/16"
        },
        {
            "title": "Locating the Hypothesis",
            "src": "http://www.hpmor.com/chapter/17"
        },
        {
            "title": "Dominance Hierarchies",
            "src": "http://www.hpmor.com/chapter/18"
        },
        {
            "title": "Delayed Gratification",
            "src": "http://www.hpmor.com/chapter/19"
        },
        {
            "title": "Bayes's Theorem",
            "src": "http://www.hpmor.com/chapter/20"
        },
        {
            "title": "Rationalization",
            "src": "http://www.hpmor.com/chapter/21"
        },
        {
            "title": "The Scientific Method",
            "src": "http://www.hpmor.com/chapter/22"
        },
        {
            "title": "Belief in Belief",
            "src": "http://www.hpmor.com/chapter/23"
        },
        {
            "title": "Machiavellian Intelligence Hypothesis",
            "src": "http://www.hpmor.com/chapter/24"
        },
        {
            "title": "Hold Off on Proposing Solutions",
            "src": "http://www.hpmor.com/chapter/25"
        },
        {
            "title": "Noticing Confusion",
            "src": "http://www.hpmor.com/chapter/26"
        },
        {
            "title": "Empathy",
            "src": "http://www.hpmor.com/chapter/27"
        },
        {
            "title": "Reductionism",
            "src": "http://www.hpmor.com/chapter/28"
        },
        {
            "title": "Egocentric Bias",
            "src": "http://www.hpmor.com/chapter/29"
        },
        {
            "title": "Working in Groups, Pt 1",
            "src": "http://www.hpmor.com/chapter/30"
        },
        {
            "title": "Working in Groups, Pt 2",
            "src": "http://www.hpmor.com/chapter/31"
        },
        {
            "title": "Interlude: Personal Financial Management",
            "src": "http://www.hpmor.com/chapter/32"
        },
        {
            "title": "Coordination Problems, Pt 1",
            "src": "http://www.hpmor.com/chapter/33"
        },
        {
            "title": "Coordination Problems, Pt 2",
            "src": "http://www.hpmor.com/chapter/34"
        },
        {
            "title": "Coordination Problems, Pt 3",
            "src": "http://www.hpmor.com/chapter/35"
        },
        {
            "title": "Status Differentials",
            "src": "http://www.hpmor.com/chapter/36"
        },
        {
            "title": "Interlude: Crossing the Boundary",
            "src": "http://www.hpmor.com/chapter/37"
        },
        {
            "title": "The Cardinal Sin",
            "src": "http://www.hpmor.com/chapter/38"
        },
        {
            "title": "Pretending to be Wise, Pt 1",
            "src": "http://www.hpmor.com/chapter/39"
        },
        {
            "title": "Pretending to be Wise, Pt 2",
            "src": "http://www.hpmor.com/chapter/40"
        },
        {
            "title": "Frontal Override",
            "src": "http://www.hpmor.com/chapter/41"
        },
        {
            "title": "Courage",
            "src": "http://www.hpmor.com/chapter/42"
        },
        {
            "title": "Humanism, Pt 1",
            "src": "http://www.hpmor.com/chapter/43"
        },
        {
            "title": "Humanism, Pt 2",
            "src": "http://www.hpmor.com/chapter/44"
        },
        {
            "title": "Humanism, Pt 3",
            "src": "http://www.hpmor.com/chapter/45"
        },
        {
            "title": "Humanism, Pt 4",
            "src": "http://www.hpmor.com/chapter/46"
        },
        {
            "title": "Personhood Theory",
            "src": "http://www.hpmor.com/chapter/47"
        },
        {
            "title": "Utilitarian Priorities",
            "src": "http://www.hpmor.com/chapter/48"
        },
        {
            "title": "Prior Information",
            "src": "http://www.hpmor.com/chapter/49"
        },
        {
            "title": "Self Centeredness",
            "src": "http://www.hpmor.com/chapter/50"
        },
        {
            "title": "Title Redacted, Pt 1",
            "src": "http://www.hpmor.com/chapter/51"
        },
        {
            "title": "The Stanford Prison Experiment, Pt 2",
            "src": "http://www.hpmor.com/chapter/52"
        },
        {
            "title": "The Stanford Prison Experiment, Pt 3",
            "src": "http://www.hpmor.com/chapter/53"
        },
        {
            "title": "The Stanford Prison Experiment, Pt 4",
            "src": "http://www.hpmor.com/chapter/54"
        },
        {
            "title": "The Stanford Prison Experiment, Pt 5",
            "src": "http://www.hpmor.com/chapter/55"
        },
        {
            "title": "TSPE, Constrained Optimization, Pt 6",
            "src": "http://www.hpmor.com/chapter/56"
        },
        {
            "title": "TSPE, Constrained Cognition, Pt 7",
            "src": "http://www.hpmor.com/chapter/57"
        },
        {
            "title": "TSPE, Constrained Cognition, Pt 8",
            "src": "http://www.hpmor.com/chapter/58"
        },
        {
            "title": "TSPE, Curiosity, Pt 9",
            "src": "http://www.hpmor.com/chapter/59"
        },
        {
            "title": "The Stanford Prison Experiment, Pt 10",
            "src": "http://www.hpmor.com/chapter/60"
        },
        {
            "title": "TSPE, Secrecy and Openness, Pt 11",
            "src": "http://www.hpmor.com/chapter/61"
        },
        {
            "title": "The Stanford Prison Experiment, Final",
            "src": "http://www.hpmor.com/chapter/62"
        },
        {
            "title": "TSPE, Aftermaths",
            "src": "http://www.hpmor.com/chapter/63"
        },
        {
            "title": "Omake Files 4, Alternate Parallels",
            "src": "http://www.hpmor.com/chapter/64"
        },
        {
            "title": "Contagious Lies",
            "src": "http://www.hpmor.com/chapter/65"
        },
        {
            "title": "Self Actualization, Pt 1",
            "src": "http://www.hpmor.com/chapter/66"
        },
        {
            "title": "Self Actualization, Pt 2",
            "src": "http://www.hpmor.com/chapter/67"
        },
        {
            "title": "Self Actualization, Pt 3",
            "src": "http://www.hpmor.com/chapter/68"
        },
        {
            "title": "Self Actualization, Pt 4",
            "src": "http://www.hpmor.com/chapter/69"
        },
        {
            "title": "Self Actualization, Pt 5",
            "src": "http://www.hpmor.com/chapter/70"
        },
        {
            "title": "Self Actualization, Pt 6",
            "src": "http://www.hpmor.com/chapter/71"
        },
        {
            "title": "SA, Plausible Deniability, Pt 7",
            "src": "http://www.hpmor.com/chapter/72"
        },
        {
            "title": "SA, The Sacred and the Mundane, Pt 8",
            "src": "http://www.hpmor.com/chapter/73"
        },
        {
            "title": "SA, Escalation of Conflicts, Pt 9",
            "src": "http://www.hpmor.com/chapter/74"
        },
        {
            "title": "Self Actualization Final, Responsibility",
            "src": "http://www.hpmor.com/chapter/75"
        },
        {
            "title": "Interlude with the Confessor: Sunk Costs",
            "src": "http://www.hpmor.com/chapter/76"
        },
        {
            "title": "SA, Aftermaths: Surface Appearances",
            "src": "http://www.hpmor.com/chapter/77"
        },
        {
            "title": "Taboo Tradeoffs Prelude: Cheating",
            "src": "http://www.hpmor.com/chapter/78"
        },
        {
            "title": "Taboo Tradeoffs, Pt 1",
            "src": "http://www.hpmor.com/chapter/79"
        },
        {
            "title": "Taboo Tradeoffs, Pt 2, The Horns Effect",
            "src": "http://www.hpmor.com/chapter/80"
        },
        {
            "title": "Taboo Tradeoffs, Pt 3",
            "src": "http://www.hpmor.com/chapter/81"
        },
        {
            "title": "Taboo Tradeoffs, Final",
            "src": "http://www.hpmor.com/chapter/82"
        },
        {
            "title": "Taboo Tradeoffs, Aftermath 1",
            "src": "http://www.hpmor.com/chapter/83"
        },
        {
            "title": "Taboo Tradeoffs, Aftermath 2",
            "src": "http://www.hpmor.com/chapter/84"
        },
        {
            "title": "Taboo Tradeoffs, Aftermath 3, Distance",
            "src": "http://www.hpmor.com/chapter/85"
        },
        {
            "title": "Multiple Hypothesis Testing",
            "src": "http://www.hpmor.com/chapter/86"
        },
        {
            "title": "Hedonic Awareness",
            "src": "http://www.hpmor.com/chapter/87"
        },
        {
            "title": "Time Pressure, Pt 1",
            "src": "http://www.hpmor.com/chapter/88"
        },
        {
            "title": "Time Pressure, Pt 2",
            "src": "http://www.hpmor.com/chapter/89"
        },
        {
            "title": "Roles, Pt 1",
            "src": "http://www.hpmor.com/chapter/90"
        },
        {
            "title": "Roles, Pt 2",
            "src": "http://www.hpmor.com/chapter/91"
        },
        {
            "title": "Roles, Pt 3",
            "src": "http://www.hpmor.com/chapter/92"
        },
        {
            "title": "Roles, Pt 4",
            "src": "http://www.hpmor.com/chapter/93"
        },
        {
            "title": "Roles, Pt 5",
            "src": "http://www.hpmor.com/chapter/94"
        },
        {
            "title": "Roles, Pt 6",
            "src": "http://www.hpmor.com/chapter/95"
        },
        {
            "title": "Roles, Pt 7",
            "src": "http://www.hpmor.com/chapter/96"
        },
        {
            "title": "Roles, Pt 8",
            "src": "http://www.hpmor.com/chapter/97"
        },
        {
            "title": "Roles, Final",
            "src": "http://www.hpmor.com/chapter/98"
        },
        {
            "title": "Roles, Aftermath",
            "src": "http://www.hpmor.com/chapter/99"
        },
        {
            "title": "Precautionary Measures, Pt 1",
            "src": "http://www.hpmor.com/chapter/100"
        },
        {
            "title": "Precautionary Measures, Pt 2",
            "src": "http://www.hpmor.com/chapter/101"
        },
        {
            "title": "Caring",
            "src": "http://www.hpmor.com/chapter/102"
        },
        {
            "title": "Tests",
            "src": "http://www.hpmor.com/chapter/103"
        },
        {
            "title": "The Truth, Pt 1, Riddles and Answers",
            "src": "http://www.hpmor.com/chapter/104"
        },
        {
            "title": "The Truth, Pt 2",
            "src": "http://www.hpmor.com/chapter/105"
        },
        {
            "title": "The Truth, Pt 3",
            "src": "http://www.hpmor.com/chapter/106"
        },
        {
            "title": "The Truth, Pt 4",
            "src": "http://www.hpmor.com/chapter/107"
        },
        {
            "title": "The Truth, Pt 5, Answers and Riddles",
            "src": "http://www.hpmor.com/chapter/108"
        },
        {
            "title": "Reflections",
            "src": "http://www.hpmor.com/chapter/109"
        },
        {
            "title": "Reflections, Pt 2",
            "src": "http://www.hpmor.com/chapter/110"
        },
        {
            "title": "Failure, Pt 1",
            "src": "http://www.hpmor.com/chapter/111"
        },
        {
            "title": "Failure, Pt 2",
            "src": "http://www.hpmor.com/chapter/112"
        },
        {
            "title": "Final Exam",
            "src": "http://www.hpmor.com/chapter/113"
        },
        {
            "title": "Shut Up and Do The Impossible",
            "src": "http://www.hpmor.com/chapter/114"
        },
        {
            "title": "Shut Up and Do The Impossible, Pt 2",
            "src": "http://www.hpmor.com/chapter/115"
        },
        {
            "title": "Aftermath, Something to Protect, Pt 0",
            "src": "http://www.hpmor.com/chapter/116"
        },
        {
            "title": "Something to Protect: Minerva McGonagall",
            "src": "http://www.hpmor.com/chapter/117"
        },
        {
            "title": "Something to Protect: Professor Quirrell",
            "src": "http://www.hpmor.com/chapter/118"
        },
        {
            "title": "Something to Protect: Albus Dumbledore",
            "src": "http://www.hpmor.com/chapter/119"
        },
        {
            "title": "Something to Protect: Draco Malfoy",
            "src": "http://www.hpmor.com/chapter/120"
        },
        {
            "title": "Something to Protect: Severus Snape",
            "src": "http://www.hpmor.com/chapter/121"
        },
        {
            "title": "Something to Protect: Hermione Granger",
            "src": "http://www.hpmor.com/chapter/122"
        }
    ]
}
